<?xml version="1.0" encoding="ISO-8859-1" standalone="no"?>
<List_Of_Chapter xmlns:xsi="http://www.w3.org/2001/XMLSchema-instance">
  <Chapter>
    <Provider_Id>1-101639606</Provider_Id>
    <Location_Id>1-131454357</Location_Id>
    <Chapter_Number>CH3</Chapter_Number>
    <Score>1</Score>
    <Action_Code>I</Action_Code>
  </Chapter>
  <Chapter>
    <Provider_Id>RJL</Provider_Id>
    <Location_Id>RJLX1</Location_Id>
    <Chapter_Number>CH3</Chapter_Number>
    <Score>1</Score>
    <Action_Code>I</Action_Code>
  </Chapter>
  <Chapter>
    <Provider_Id>1-101606400</Provider_Id>
    <Location_Id>1-111111111</Location_Id>
    <Chapter_Number>CH3</Chapter_Number>
    <Score>1</Score>
    <Action_Code>I</Action_Code>
  </Chapter>
</List_Of_Chapter>
